.coveragerc
.csslintrc
.eslintrc
AUTHORS
CHANGELOG.rst
LICENSE
MANIFEST.in
README.rst
karma.conf.js
package.json
pyproject.toml
setup.cfg
setup.py
tidy.js
tox.ini
.circleci/config.yml
Mopidy_MusicBox_Darkclient.egg-info/PKG-INFO
Mopidy_MusicBox_Darkclient.egg-info/SOURCES.txt
Mopidy_MusicBox_Darkclient.egg-info/dependency_links.txt
Mopidy_MusicBox_Darkclient.egg-info/entry_points.txt
Mopidy_MusicBox_Darkclient.egg-info/not-zip-safe
Mopidy_MusicBox_Darkclient.egg-info/requires.txt
Mopidy_MusicBox_Darkclient.egg-info/top_level.txt
mopidy_musicbox_darkclient/__init__.py
mopidy_musicbox_darkclient/ext.conf
mopidy_musicbox_darkclient/web.py
mopidy_musicbox_darkclient/webclient.py
mopidy_musicbox_darkclient/locale/messages.pot
mopidy_musicbox_darkclient/locale/ru/LC_MESSAGES/messages.mo
mopidy_musicbox_darkclient/locale/ru/LC_MESSAGES/messages.po
mopidy_musicbox_darkclient/static/dialog-success.html
mopidy_musicbox_darkclient/static/index.html
mopidy_musicbox_darkclient/static/index_fix.html
mopidy_musicbox_darkclient/static/mb.appcache
mopidy_musicbox_darkclient/static/system.html
mopidy_musicbox_darkclient/static/css/webclient.css
mopidy_musicbox_darkclient/static/images/default_cover.png
mopidy_musicbox_darkclient/static/images/empty.png
mopidy_musicbox_darkclient/static/images/loader.gif
mopidy_musicbox_darkclient/static/images/user_24x32.png
mopidy_musicbox_darkclient/static/images/icons/musicbox114.png
mopidy_musicbox_darkclient/static/images/icons/musicbox32.gif
mopidy_musicbox_darkclient/static/images/icons/musicbox32.png
mopidy_musicbox_darkclient/static/images/icons/musicbox57.png
mopidy_musicbox_darkclient/static/images/icons/musicbox72.png
mopidy_musicbox_darkclient/static/images/icons/play_alt_12x12.png
mopidy_musicbox_darkclient/static/images/icons/play_alt_16x16.png
mopidy_musicbox_darkclient/static/js/controls.js
mopidy_musicbox_darkclient/static/js/custom_scripting.js
mopidy_musicbox_darkclient/static/js/functionsvars.js
mopidy_musicbox_darkclient/static/js/gui.js
mopidy_musicbox_darkclient/static/js/i18n.js
mopidy_musicbox_darkclient/static/js/images.js
mopidy_musicbox_darkclient/static/js/library.js
mopidy_musicbox_darkclient/static/js/master.js
mopidy_musicbox_darkclient/static/js/process_ws.js
mopidy_musicbox_darkclient/static/js/synced_timer.js
mopidy_musicbox_darkclient/static/locale/ru.js
