Metadata-Version: 2.1
Name: Mopidy-MusicBox-Darkclient
Version: 1.0.6
Summary: Mopidy MusicBox web extension dark theme
Home-page: https://github.com/stffart/mopidy-musicbox-darkclient
Author: stffart, Wouter van Wijk
Author-email: stffart@gmail.com
License: Apache License, Version 2.0
Platform: UNKNOWN
Classifier: Environment :: No Input/Output (Daemon)
Classifier: Intended Audience :: End Users/Desktop
Classifier: License :: OSI Approved :: Apache Software License
Classifier: Operating System :: OS Independent
Classifier: Programming Language :: Python :: 3
Classifier: Programming Language :: Python :: 3.7
Classifier: Programming Language :: Python :: 3.8
Classifier: Topic :: Multimedia :: Sound/Audio :: Players
Requires-Python: >=3.7
Provides-Extra: dev
Provides-Extra: lint
Provides-Extra: node
Provides-Extra: release
Provides-Extra: test
